[{"node":{"name":"Rosemary Ranch Chicken Kabobs","cuisines":["Greek"],"ingredients":[{"name":"Olive oil"},{"name":"Ranch dressing"},{"name":"Worchestire sauce"},{"name":"Salt"},{"name":"Lemon juice"},{"name":"White vinegar"},{"name":"Black pepper"},{"name":"Chicken breast"}]}},{"node":{"name":"Air Fryer Greek Frittata","cuisines":["American","Kid-Friendly","Greek"],"ingredients":[{"name":"Eggs"},{"name":"Heavy whipping cream"},{"name":"Spinach"},{"name":"Zucchini"},{"name":"Cherry tomatoes"},{"name":"Red onion"},{"name":"Oregano"},{"name":"Salt"},{"name":"Black pepper"}]}},{"node":{"name":"Warm Feta With Tomatoes And Olives","cuisines":["Greek"],"ingredients":[{"name":"Feta cheese"},{"name":"Cherry tomatoes"},{"name":"Olives"},{"name":"Olive oil"},{"name":"Lemon juice"}]}},{"node":{"name":"Greek Salmon","cuisines":["Greek"],"ingredients":[{"name":"Salmon"},{"name":"Olive oil"},{"name":"Lemon juice"},{"name":"Dill"},{"name":"Garlic"},{"name":"Salt"},{"name":"Black pepper"}]}},{"node":{"name":"Greek Omelet","cuisines":["Greek"],"ingredients":[{"name":"Eggs"},{"name":"Salt"},{"name":"Black pepper"},{"name":"Olive oil"},{"name":"Cherry tomatoes"},{"name":"Feta cheese"},{"name":"Parsley"}]}},{"node":{"name":"Greek Tomato Rice","cuisines":["Greek"],"ingredients":[{"name":"Olive oil"},{"name":"Onion"},{"name":"Garlic"},{"name":"Rice"},{"name":"Vegetable broth"},{"name":"Tomato sauce"},{"name":"Salt"}]}},{"node":{"name":"Vegan Greek Lentil Soup","cuisines":["Greek"],"ingredients":[{"name":"Lentils"},{"name":"Olive oil"},{"name":"Garlic"},{"name":"Onion"},{"name":"Carrots"},{"name":"Rosemary leaves"},{"name":"Bay leaves"},{"name":"Tomato paste"},{"name":"Salt"},{"name":"Black pepper"},{"name":"Red wine vinegar"}]}},{"node":{"name":"Mexican Greek Stuffed Green Peppers","cuisines":["Mexican","Greek","Kid-Friendly"],"ingredients":[{"name":"Beef"},{"name":"Water"},{"name":"Taco seasoning"},{"name":"Rice"},{"name":"Tomato soup"},{"name":"Tomato"},{"name":"Mushrooms"},{"name":"Red onion"},{"name":"Feta cheese"},{"name":"Green onion"},{"name":"Bell peppers"},{"name":"Kalamata olives"}]}},{"node":{"name":"Greek Shrimp With Tomatoes & Feta","cuisines":["Greek"],"ingredients":[{"name":"Shrimp"},{"name":"Olive oil"},{"name":"Garlic"},{"name":"Salt"},{"name":"Black pepper"},{"name":"Onion"},{"name":"Oregano"},{"name":"Tomatoes"},{"name":"White wine"},{"name":"Parsley"},{"name":"Feta cheese"}]}},{"node":{"name":"Greek White Bean Soup","cuisines":["Greek"],"ingredients":[{"name":"Olive oil"},{"name":"Cans of cannellini beans"},{"name":"Onion"},{"name":"Carrots"},{"name":"Celery stick"},{"name":"Garlic cloves"},{"name":"Tomato paste"},{"name":"Tomatoes"},{"name":"Rosemary leaves"},{"name":"Red chili flake"},{"name":"Bay leaves"},{"name":"Vegetable broth"},{"name":"Salt"}]}},{"node":{"name":"Caprese Tomato-Basil Soup","cuisines":["Mediterranean","Greek","Italian"],"ingredients":[{"name":"Red onion"},{"name":"Olive oil"},{"name":"Garlic"},{"name":"Tomatoes"},{"name":"Yeast"},{"name":"Vegetable broth"},{"name":"Basil"},{"name":"Tomato paste"},{"name":"Greek yogurt"},{"name":"Salt"}]}},{"node":{"name":"Chicken Souvlaki","cuisines":["Kid-Friendly","Greek"],"ingredients":[{"name":"Olive oil"},{"name":"Garlic"},{"name":"Lemon juice"},{"name":"Oregano"},{"name":"Salt"},{"name":"Chicken breast"}]}},{"node":{"name":"Greek Spinach Rice","cuisines":["Greek"],"ingredients":[{"name":"Olive oil"},{"name":"White rice"},{"name":"Salt"},{"name":"Black pepper"},{"name":"Cayenne pepper"},{"name":"Green onion"},{"name":"Dill"},{"name":"Spinach"},{"name":"Lemon"},{"name":"Feta cheese"},{"name":"Chili flakes"}]}},{"node":{"name":"Vegan Potato Sauerkraut Pancakes","cuisines":["Greek"],"ingredients":[{"name":"Potatoes"},{"name":"Sauerkraut"},{"name":"Rosemary leaves"},{"name":"Chives"},{"name":"All purpose flour"},{"name":"Baking soda"},{"name":"Salt"},{"name":"Black pepper"},{"name":"Olive oil"}]}},{"node":{"name":"Greek Peas With Tomato And Dill","cuisines":["Greek"],"ingredients":[{"name":"Olive oil"},{"name":"Green onions"},{"name":"Peas"},{"name":"Carrots"},{"name":"Tomatoes"},{"name":"Potato"},{"name":"Dill"},{"name":"Water"},{"name":"Salt"},{"name":"Black pepper"}]}},{"node":{"name":"Greek Stewed Green Beans","cuisines":["Greek"],"ingredients":[{"name":"Olive oil"},{"name":"Onion"},{"name":"Green beans"},{"name":"Tomatoes"},{"name":"Potato"},{"name":"Salt"},{"name":"Black pepper"}]}},{"node":{"name":"Grilled Spatchcooked Greek Chicken","cuisines":["Kid-Friendly","Greek"],"ingredients":[{"name":"Olive oil"},{"name":"Lemon juice"},{"name":"Oregano"},{"name":"Garlic"},{"name":"Rosemary leaves"},{"name":"Tarragon leaves"},{"name":"Chicken"},{"name":"Salt"},{"name":"Black pepper"}]}},{"node":{"name":"Lemon Chicken And Potatoes","cuisines":["Greek"],"ingredients":[{"name":"Chicken thighs"},{"name":"Salt"},{"name":"Oregano"},{"name":"Black pepper"},{"name":"Rosemary leaves"},{"name":"Cayenne pepper"},{"name":"Lemon juice"},{"name":"Olive oil"},{"name":"Garlic cloves"},{"name":"Potatoes"},{"name":"Vegetable broth"}]}},{"node":{"name":"Chicken Orzo Lemon Soup","cuisines":["Greek"],"ingredients":[{"name":"Chicken broth"},{"name":"Orzo"},{"name":"Eggs"},{"name":"Lemon juice"},{"name":"Olive oil"},{"name":"Garlic"},{"name":"Salt"},{"name":"Black pepper"},{"name":"Chicken breasts"},{"name":"Shallots"},{"name":"Lemon"},{"name":"Parsley"}]}},{"node":{"name":"Greek Style Garlic Chicken Breast","cuisines":["Kid-Friendly","Greek"],"ingredients":[{"name":"Chicken breasts"},{"name":"Olive oil"},{"name":"Lemon"},{"name":"Garlic"},{"name":"Salt"},{"name":"Black pepper"},{"name":"Paprika"}]}},{"node":{"name":"Greek Grilled Chicken","cuisines":["Kid-Friendly","Greek"],"ingredients":[{"name":"Garlic"},{"name":"Oregano"},{"name":"Black pepper"},{"name":"Red pepper flakes"},{"name":"Lemon juice"},{"name":"Olive oil"},{"name":"White vinegar"},{"name":"Chicken legs"}]}}]